{
  "sections": {
    "main": {
      "type": "main-product",
      "blocks": {
        "vendor": {
          "type": "text",
          "settings": {
            "text": "{{ product.vendor }}",
            "text_style": "uppercase"
          }
        },
        "title": {
          "type": "title",
          "settings": {
          }
        },
        "subtitle": {
          "type": "text",
          "settings": {
            "text": "{{ product.metafields.descriptors.subtitle.value }}",
            "text_style": "subtitle"
          }
        },
        "price": {
          "type": "price",
          "settings": {
          }
        },
        "variant_picker": {
          "type": "variant_picker",
          "settings": {
            "picker_type": "button"
          }
        },
        "quantity_selector": {
          "type": "quantity_selector",
          "settings": {
          }
        },
        "buy_buttons": {
          "type": "buy_buttons",
          "settings": {
            "show_dynamic_checkout": true
          }
        },
        "description": {
          "type": "description",
          "settings": {
          }
        },
        "share": {
          "type": "share",
          "settings": {
          }
        }
      },
      "block_order": [
        "vendor",
        "title",
        "subtitle",
        "price",
        "variant_picker",
        "quantity_selector",
        "buy_buttons",
        "description",
        "share"
      ],
      "settings": {
        "enable_sticky_info": true,
        "enable_video_looping": false
      }
    },
    "162994917204089a3d": {
      "type": "image-with-text",
      "blocks": {
        "f0489dc6-fb41-4029-b2ef-e76428de518e": {
          "type": "preheading",
          "settings": {
            "preheading": "COMMUNITY SUPPORTED WINE CLUB"
          }
        },
        "162994917204089a3d-0": {
          "type": "heading",
          "settings": {
            "heading": "Come On In"
          }
        },
        "162994917204089a3d-1": {
          "type": "text",
          "settings": {
            "text": "<p>This club makes our world go around so we want every release to feel special for you. Our club members receive a bottle of each new wine along with:<br\/><br\/>• First access to new vintages and special releases<\/p><p>• Limited edition artwork and thoughtful club goodies<\/p><p>• $25 flat rate shipping on all orders<\/p><p>• Tickets to release parties, popups and other events<\/p>"
          }
        },
        "162994917204089a3d-2": {
          "type": "button",
          "settings": {
            "button_label": "Join Now",
            "button_link": "shopify:\/\/pages\/6-bottle-membership-signup"
          }
        }
      },
      "block_order": [
        "f0489dc6-fb41-4029-b2ef-e76428de518e",
        "162994917204089a3d-0",
        "162994917204089a3d-1",
        "162994917204089a3d-2"
      ],
      "settings": {
        "image": "shopify:\/\/shop_images\/759e98e1db7c669de0d6b078a93667c9.jpg",
        "mask": true,
        "wine_club": true,
        "thin": false,
        "layout": "image_first"
      }
    },
    "product-recommendations": {
      "type": "product-recommendations",
      "settings": {
        "heading": "You may also like",
        "image_ratio": "adapt",
        "show_secondary_image": false,
        "add_image_padding": false,
        "show_vendor": false
      }
    }
  },
  "order": [
    "main",
    "162994917204089a3d",
    "product-recommendations"
  ]
}
